mathease/__init__.py
mathease-0.0.1.dist-info/METADATA
mathease-0.0.1.dist-info/WHEEL
mathease-0.0.1.dist-info/top_level.txt
mathease-0.0.1.dist-info/RECORD
