Metadata-Version: 2.1
Name: mathease
Version: 0.0.1
Summary: A practical mathematical toolbox for Python.
Author-email: Freedeaths <register917@gmail.com>
Classifier: Programming Language :: Python :: 3
Classifier: License :: OSI Approved :: MIT License
Classifier: Operating System :: OS Independent
Requires-Python: >=3.11
